Lab1/Task2/half_adder.sv
module half_adder #(
    parameter Width=2
) (
    input [Width-1:0] A,B,
    output [Width-1:0] S,output C
);

   xor a1(S[0],A[0],B[0]);
   and a2(X,A[0],B[0]);

   xor a3(S[1],A[1],B[1],X);
   xor a6(Z,A[1],B[1]);
   and a4(Y,A[1],B[1]);

   and a8(I,X,Z);

   or a5(C,I,Y);

   
endmodule

Lab1/Task2/full_adder.sv
`include "half_adder.sv"
module full_adder #(
    parameter Width=2
) (
    input [Width-1:0] A,B,C_in,
    output [Width-1:0] S,output C_out
);

    wire [1:0] X;
    wire Y,Z;

    half_adder a1 (.A(C_in),.B(X),.S(S),.C(Y));
    half_adder a2(.A(A),.B(B),.S(X),.C(Z));

    or a3(C_out,Y,Z);

   initial begin
       $dumpfile("dump.vcd");
       $dumpvars;
   end

endmodule

Lab1/Task2/dump.vcd
$date
	Sat Sep 25 21:11:01 2021
$end
$version
	Icarus Verilog
$end
$timescale
	1ps
$end
$scope module full_adder $end
$var wire 2 ! A [1:0] $end
$var wire 2 " B [1:0] $end
$var wire 2 # C_in [1:0] $end
$var wire 1 $ C_out $end
$var wire 1 % Z $end
$var wire 1 & Y $end
$var wire 2 ' X [1:0] $end
$var wire 2 ( S [1:0] $end
$scope module a1 $end
$var wire 2 ) A [1:0] $end
$var wire 1 & C $end
$var wire 1 * I $end
$var wire 1 + X $end
$var wire 1 , Y $end
$var wire 1 - Z $end
$var wire 2 . S [1:0] $end
$var wire 2 / B [1:0] $end
$upscope $end
$scope module a2 $end
$var wire 2 0 A [1:0] $end
$var wire 2 1 B [1:0] $end
$var wire 1 % C $end
$var wire 1 2 I $end
$var wire 1 3 X $end
$var wire 1 4 Y $end
$var wire 1 5 Z $end
$var wire 2 6 S [1:0] $end
$upscope $end
$upscope $end
$enddefinitions $end
#0
$dumpvars
b0 6
05
04
03
02
b0 1
b0 0
b0 /
b0 .
0-
0,
0+
0*
b0 )
b0 (
b0 '
0&
0%
0$
b0 #
b0 "
b0 !
$end
#2000
b1 (
b1 .
b1 #
b1 )
#4000
b1 '
b1 /
b1 6
b1 (
b1 .
b1 "
b1 1
b0 #
b0 )
#6000
b10 (
b10 .
1+
b1 #
b1 )
#8000
1-
b10 '
b10 /
b10 6
15
b10 (
b10 .
0+
b10 "
b10 1
b0 #
b0 )
#10000
b11 (
b11 .
b1 #
b1 )
#12000
b11 '
b11 /
b11 6
b11 (
b11 .
b11 "
b11 1
b0 #
b0 )
#14000
1$
1&
1*
b0 (
b0 .
1+
b1 #
b1 )
#16000
0$
0-
0&
0*
b1 '
b1 /
b1 6
05
b1 (
b1 .
0+
b1 !
b1 0
b0 "
b0 1
b0 #
b0 )
#18000
b10 (
b10 .
1+
b1 #
b1 )
#20000
1-
b10 '
b10 /
b10 6
13
b10 (
b10 .
0+
b1 "
b1 1
b0 #
b0 )
#22000
b11 (
b11 .
b1 #
b1 )
#24000
1-
03
b11 '
b11 /
b11 6
15
b11 (
b11 .
b10 "
b10 1
b0 #
b0 )
#26000
1$
1&
1*
b0 (
b0 .
1+
b1 #
b1 )
#28000
0-
1%
0&
12
0*
b0 '
b0 /
b0 6
13
b0 (
b0 .
0+
b11 "
b11 1
b0 #
b0 )
#30000
b1 (
b1 .
b1 #
b1 )
#32000
1-
0$
0%
b10 '
b10 /
b10 6
02
03
b10 (
b10 .
b10 !
b10 0
b0 "
b0 1
b0 #
b0 )
#34000
b11 (
b11 .
b1 #
b1 )
#36000
b11 '
b11 /
b11 6
b11 (
b11 .
b1 "
b1 1
b0 #
b0 )
#38000
1$
1&
1*
b0 (
b0 .
1+
b1 #
b1 )
#40000
0-
0&
1%
0*
b0 '
b0 /
b0 6
05
14
b0 (
b0 .
0+
b10 "
b10 1
b0 #
b0 )
#42000
b1 (
b1 .
b1 #
b1 )
#44000
b1 '
b1 /
b1 6
b1 (
b1 .
b11 "
b11 1
b0 #
b0 )
#46000
b10 (
b10 .
1+
b1 #
b1 )
#48000
1-
0$
0%
b11 '
b11 /
b11 6
15
04
b11 (
b11 .
0+
b11 !
b11 0
b0 "
b0 1
b0 #
b0 )
#50000
1$
1&
1*
b0 (
b0 .
1+
b1 #
b1 )
#52000
0-
1%
0&
12
0*
b0 '
b0 /
b0 6
13
b0 (
b0 .
0+
b1 "
b1 1
b0 #
b0 )
#54000
b1 (
b1 .
b1 #
b1 )
#56000
0-
02
03
b1 '
b1 /
b1 6
05
14
b1 (
b1 .
b10 "
b10 1
b0 #
b0 )
#58000
b10 (
b10 .
1+
b1 #
b1 )
#60000
1-
b10 '
b10 /
b10 6
13
b10 (
b10 .
0+
b11 "
b11 1
b0 #
b0 )
#62000
b11 (
b11 .
b1 #
b1 )
