Pipelined/srcs/Controller.sv
module Controller (
    input [31:0] Instruction,
    output reg [3:0] alu_op,output reg reg_wr, sel_A, sel_B,
    wr_en, rd_en, unsign,output reg [2:0] br_type, output reg [1:0] wb_sel
);  
    wire [6:0] opcode, func7 ;
    wire [2:0] func3;
    assign opcode = Instruction[6:0];
    assign func7 = Instruction[31:25];
    assign func3 = Instruction[14:12];
    always_comb begin 
        alu_op = 0;
        reg_wr = 0;
        sel_A = 0;
        sel_B = 0;
        wr_en = 0;
        rd_en = 0;
        wb_sel = 0;
        br_type = 3'b111;
        unsign = 0;
        case (opcode)
            // I type load
            7'd3: begin
                reg_wr = 1;
                sel_B = 1;
                rd_en = 1;
                wb_sel = 2;
            end
            // S type sw only
            7'd35: begin
                sel_B = 1;
                wr_en = 1;
                wb_sel = 2;
            end
            // I type
            7'd19: begin
                reg_wr = 1;
                sel_B = 1;
                rd_en = 1;
                wb_sel = 1;
                case (func3)
                    7'd0: alu_op = 0;
                    7'd1: begin
                        alu_op = 1;
                        unsign = 1;
                    end 
                    7'd2: begin
                        alu_op = 10;
                    end
                    7'd3: begin
                        alu_op = 10;
                        unsign = 1;
                    end
                    7'd4: begin
                        alu_op = 2;
                    end
                    7'd5: begin
                        case(func7)
                        7'b0 : alu_op = 3;
                        7'b0100000: alu_op = 4;
                        default: alu_op = 3;
                        endcase
                    end
                    7'd6: alu_op = 5;
                    7'd7: alu_op = 6;
                    default: alu_op = 0;
                endcase
            end
            // U Type auipc
            7'd23: begin 
                alu_op = 0;
                sel_A = 1;
                sel_B = 1;
                br_type = 6;
            end
            // U Type lui
            7'd55: begin
                alu_op = 9;
                reg_wr = 1;
                sel_B = 1;
                rd_en = 1;
                wb_sel = 1;
            end
            // R Type
            7'd51: begin
                reg_wr = 1;
                rd_en = 1;
                wb_sel = 1;
                case (func3)
                    7'd0:begin
                        case (func7)
                            7'b0: alu_op = 0;
                            7'b0100000: alu_op = 7;
                            default: alu_op = 0;
                        endcase
                    end 
                    7'd1: begin
                        alu_op = 1;
                    end 
                    7'd2: begin
                        alu_op = 10;
                    end
                    7'd3: begin
                        alu_op = 10;
                        unsign = 1;
                    end
                    7'd4: begin
                        alu_op = 2;
                    end
                    7'd5: begin
                        case(func7)
                        7'd0 : alu_op = 3;
                        7'b0100000: alu_op = 4;
                        default: alu_op = 3;
                        endcase
                    end
                    7'd6: alu_op = 5;
                    7'd7: alu_op = 6;
                    default: alu_op = 0;
                endcase
            end
            // B Type
            7'd99: begin
                sel_A = 1;
                sel_B = 1;
                case(func3)
                    0: br_type = 0;
                    1: br_type = 1;
                    4: br_type = 2;
                    5: br_type = 3;
                    6: br_type = 4;
                    7: br_type = 5;
                default: br_type = 7;
                endcase
            end 
            // I JALR
            7'd103: begin
                sel_A = 1;
                sel_B = 1;
                wb_sel = 1;
                reg_wr = 1;
                br_type = 6;
            end
            // J Type
            7'd111: begin
                sel_A = 1;
                sel_B = 1;
                br_type = 6;
                reg_wr = 1;
                wb_sel = 0;
            end
            // csr
            7'd115: begin
                if(func3 != 0) begin
                reg_wr = 1;
                sel_B = 1;
                rd_en = 1;
                wb_sel = 4;
                alu_op = 8;
                end
            end
            //default: 
        endcase
    end
    
endmodule

Pipelined/srcs/Data_Memory.sv
module Data_Memory (
    output reg [31:0] result,
    output reg [31:0] rdata,
    input [31:0] wdata, addr, num1, num2,
    input wr_en, rd_en, clk, rst, hard_write
);

    reg [8:0] data_mem [255:0];
    integer i;

    always @(*) begin
        if(rd_en)
            rdata <= {data_mem[addr],data_mem[addr+1],data_mem[addr+2],data_mem[addr+3]};
    end

    always @(posedge clk) begin
            result <= {data_mem[8],data_mem[8+1],data_mem[8+2],data_mem[8+3]};
    end

    always @(posedge clk) begin
        if(rst) begin
            {data_mem[0],data_mem[0+1],data_mem[0+2],data_mem[0+3]} <= num1;
            {data_mem[4],data_mem[4+1],data_mem[4+2],data_mem[4+3]} <= num2;
            for(i=8;i<=255;i=i+1) begin
                data_mem[i] <= 0;
            end
        end else begin
            if(wr_en && addr >= 8)
                {data_mem[addr],data_mem[addr+1],data_mem[addr+2],data_mem[addr+3]} <= wdata; 
        end
    end
    
endmodule

Pipelined/srcs/Branch_Condition.sv
module Branch_Condition (
    output reg br_taken,
    input [31:0] A, B,
    input [2:0] br_type
);

    always_comb begin 
        case(br_type)
            0: br_taken <= A == B;
            1: br_taken <= A != B;
            2: br_taken <= A < B;
            3: br_taken <= A > B;
            4: br_taken <= A <= B;
            5: br_taken <= A >= B;
            6: br_taken <= 1;
        default: br_taken <= 0;
        endcase
    end
    
endmodule

Single-Cycle/srcs/ALU.sv
module ALU (
    output reg [31:0] ALU_out,
    input [31:0] A, B,
    input [3:0] alu_op
);
    always_comb begin 
        case(alu_op)
            0: ALU_out = A + B;// addi
            1: ALU_out = A << B;// slli
            2: ALU_out = A ^^ B;// xor
            3: ALU_out = A >> B;// srli
            4: ALU_out = A >>> B;// srai
            5: ALU_out = A || B;// or
            6: ALU_out = A && B;// and
            7: ALU_out = A - B;
            8: ALU_out = A;
            9: ALU_out = B;
            10: ALU_out = A < B;
        default: ALU_out = A + B;
        endcase
    end
    
endmodule

Single-Cycle/Immediate_Generator.sv
module Immediate_Generator (
    output reg [31:0] Immediate_Value,
    input [31:0] Instruction,
    input unsign
);
    wire [6:0] opcode;
    assign opcode = Instruction[6:0];
    always_comb begin 
       // Using Opcode
        case (opcode)
            // I Type Instruction
            7'd3,7'd19,7'd103: Immediate_Value <= unsign ? {{20'b0}, Instruction[31:20]} : {{20{Instruction[31]}}, Instruction[31:20]};
            // S Type Instruction
            7'd35: Immediate_Value <= {{20{Instruction[31]}}, Instruction[31:25], Instruction[11:7]};
            // B Type Instruction
            7'd99: Immediate_Value <= {{20{Instruction[31]}}, Instruction[7], Instruction[30:25], Instruction[11:8], 1'b0};
            // J Type Instruction
            7'd111: Immediate_Value <= {{12{Instruction[31]}}, Instruction[19:12], Instruction[20], Instruction[30:21], 1'b0};
            // U Type Instruction
            7'd23,7'd55: Immediate_Value <= {Instruction[31:12],12'b0};
            default: Immediate_Value <= 0;
        endcase
    end
endmodule

Lab3/Program_Counter.sv
module Program_Counter (
    input [31:0] ALU_out,
    input br_taken, clk, rst, auipc, hard_write,
    output reg [31:0] PC
);
    always @(posedge clk ) begin
        if(rst || hard_write)
            PC <= 0;
        else 
            PC <= br_taken ? ALU_out : PC + 4;
    end
    
endmodule

Single-Cycle/srcs/Instruction_Memory.sv
module Instruction_Memory (
    output reg [31:0] Instruction,
    input [31:0] Address
);
    reg [31:0] instruction_memory [50:0];
    initial begin
     $readmemh("../srcs/instruction_mem.mem",instruction_memory);
    end

    always @(*) begin
        Instruction <= instruction_memory[Address/4];
    end

    initial begin
        $dumpfile("dump.vcd");
        $dumpvars;
    end
    
endmodule

Lab3/Register_File.sv
module Register_File (
    output reg [31:0] rdata1, rdata2,
    output reg [31:0] x0,x1,x2,x3,x4,x5,x6,x7,x8,x9,x10,x11,x12,x13,x14,x15,x16,x17,x18,x19,x20,x21,x22,x23,x24,x25,x26,x27,x28,x29,x30,x31,
    input [4:0] raddr1, raddr2, waddr,
    input [31:0] wdata,
    input clk, rst, reg_wr
);
    integer i;
    reg [31:0] register_file [31:0];
    always @(posedge clk ) begin
        if(rst) begin
            for (i = 0; i <= 31; i=i+1) begin
                register_file[i] <= 0;
            end
        end else if(reg_wr) begin
            if(waddr != 0)
                register_file[waddr] <= wdata;
        end 
    end

    always @(*) begin
        rdata1 <= register_file[raddr1];
        rdata2 <= register_file[raddr2];
        x0 <= register_file[0];
        x1 <= register_file[1];
        x2 <= register_file[2];
        x3 <= register_file[3];
        x4 <= register_file[4];
        x5 <= register_file[5];
        x6 <= register_file[6];
        x7 <= register_file[7];
        x8 <= register_file[8];
        x9 <= register_file[9];
        x10 <= register_file[10];
        x11 <= register_file[11];
        x12 <= register_file[12];
        x13 <= register_file[13];
        x14 <= register_file[14];
        x15 <= register_file[15];
        x16 <= register_file[16];
        x17 <= register_file[17];
        x18 <= register_file[18];
        x19 <= register_file[19];
        x20 <= register_file[20];
        x21 <= register_file[21];
        x22 <= register_file[22];
        x23 <= register_file[23];
        x24 <= register_file[24];
        x25 <= register_file[25];
        x26 <= register_file[26];
        x27 <= register_file[27];
        x28 <= register_file[28];
        x29 <= register_file[29];
        x30 <= register_file[30];
        x31 <= register_file[31];
    end

    initial begin
        $dumpfile("dump.vcd");
        $dumpvars;
    end
    
endmodule

Single-Cycle/top.sv
`include "Register_File.sv"
`include "Instruction_Memory.sv"
`include "Program_Counter.sv"
`include "Immediate_Generator.sv"
`include "ALU.sv"
`include "Branch_Condition.sv"
`include "Data_Memory.sv"
`include "Controller.sv"
`timescale 1ns/1ns

module top(
    input clk, rst
);
    
    wire[31:0] rdata1, rdata2, num1, num2, result;
    wire [31:0] x0,x1,x2,x3,x4,x5,x6,x7,x8,x9,x10,x11,x12,x13,x14,x15,x16,x17,x18,x19,x20,x21,x22,x23,x24,x25,x26,x27,x28,x29,x30,x31;
    wire [4:0] raddr1, raddr2, waddr;
    reg [31:0] wdata;
    wire [31:0] Instruction, PC, ALU_out, Immediate_Value, rdata;
    reg [31:0] A, B;
    wire [3:0] alu_op;
    wire [2:0] br_type;
    wire [1:0] wb_sel;
    wire sel_A, sel_B;

    Register_File rf(.rdata1(rdata1), .rdata2(rdata2), 
    .x0(x0), .x1(x1), .x2(x2), .x3(x3), .x4(x4), .x5(x5), .x6(x6), .x7(x7), .x8(x8), .x9(x9), .x10(x10), .x11(x11), .x12(x12), .x13(x13), .x14(x14),
    .x15(x15), .x16(x16), .x17(x17), .x18(x18), .x19(x19), .x20(x20), .x21(x21), .x22(x22), .x23(x23), .x24(x24), .x25(x25), .x26(x26), .x27(x27),
    .x28(x28), .x29(x29), .x30(x30), .x31(x31),
    .raddr1(Instruction[19:15]), .raddr2(Instruction[24:20]), .waddr(Instruction[11:7]), .wdata(wdata), .clk(clk), .rst(rst), .reg_wr(reg_wr));

    Instruction_Memory im(.Instruction(Instruction), .Address(PC));

    Program_Counter pc(.ALU_out(ALU_out), .br_taken(br_taken), .clk(clk), .rst(rst), .PC(PC), .hard_write(hard_write));

    Immediate_Generator ig(.Immediate_Value(Immediate_Value), .Instruction(Instruction), .unsign(unsign));

    always @(*) begin
        A <= sel_A ? PC : rdata1;
        B <= sel_B ? Immediate_Value : rdata2;
    end
    

    ALU al(.ALU_out(ALU_out),.A(A), .B(B),.alu_op(alu_op));

    Branch_Condition bcond(.br_taken(br_taken), .A(rdata1), .B(rdata2), .br_type(br_type));

    Data_Memory dmem(.num1(num1), .num2(num2), .result(result), .hard_write(hard_write),
                     .rdata(rdata), .wdata(rdata2), .addr(ALU_out),
                     .wr_en(wr_en), .rd_en(rd_en), .clk(clk), .rst(rst));


    always_comb begin 
        case (wb_sel)
            0 : wdata <=  PC + 4;
            1 : wdata <= ALU_out;
            2 : wdata <= rdata;
        endcase
    end 

    Controller cont(.Instruction(Instruction), .alu_op(alu_op), .reg_wr(reg_wr), .sel_A(sel_A), .sel_B(sel_B),
    .wr_en(wr_en), .rd_en(rd_en), .br_type(br_type), .wb_sel(wb_sel), .unsign(unsign));  

    initial begin
        $dumpfile("dump.vcd");
        $dumpvars;
    end
    
endmodule

Single-Cycle/Single Cycle Hardware/Single Cycle Hardware.srcs/sim_1/new/simulation.sv
`timescale 1ns / 1ps

module simulation;

    reg [31:0] num1, num2;
    reg clk, rst, hard_write;
    wire [31:0] result;
    
    top dut(num1, num2, clk, rst, hard_write, result);
    
    initial begin
        clk = 1;
        forever #5 clk = ~clk;
    end
    
    initial begin
        num1 = 2;
        num2 = 4;
        rst = 1;
        repeat(2) @(posedge clk);
        rst = 0;
        hard_write = 1;
        repeat(2) @(posedge clk);
        hard_write = 0;
        while(dut.PC != 32'd44) begin
            @(posedge clk);
            $display("value of PC is %0d",dut.PC);
        end
        @(posedge clk);
        $display("final value of PC is %0d",dut.PC);
        
        
        num1 = 30;
        num2 = 15;
        hard_write = 1;
        repeat(2) @(posedge clk);
        hard_write = 0;
        while(dut.PC != 32'd44) begin
            @(posedge clk);
            $display("value of PC is %0d",dut.PC);
        end
        @(posedge clk);
        $display("final value of PC is %0d",dut.PC);
        $stop;
    end
    
endmodule

Single-Cycle/Single Cycle Hardware/Single Cycle Hardware.sim/sim_1/behav/xsim/dump.vcd
$date
   Tue Nov  2 19:52:23 2021
$end
$version
  2018.2
$end
$timescale
  1ps
$end
$scope module simulation $end
$scope module dut $end
$var wire 32 M num1 [31:0] $end
$var wire 32 N num2 [31:0] $end
$var wire 1 G clk $end
$var wire 1 H rst $end
$var wire 1 O hard_write $end
$var wire 32 P result [31:0] $end
$var wire 32 Q rdata1 [31:0] $end
$var wire 32 R rdata2 [31:0] $end
$var wire 32 S x0 [31:0] $end
$var wire 32 T x1 [31:0] $end
$var wire 32 U x2 [31:0] $end
$var wire 32 V x3 [31:0] $end
$var wire 32 W x4 [31:0] $end
$var wire 32 X x5 [31:0] $end
$var wire 32 Y x6 [31:0] $end
$var wire 32 Z x7 [31:0] $end
$var wire 32 [ x8 [31:0] $end
$var wire 32 \ x9 [31:0] $end
$var wire 32 ] x10 [31:0] $end
$var wire 32 ^ x11 [31:0] $end
$var wire 32 _ x12 [31:0] $end
$var wire 32 ` x13 [31:0] $end
$var wire 32 a x14 [31:0] $end
$var wire 32 b x15 [31:0] $end
$var wire 32 c x16 [31:0] $end
$var wire 32 d x17 [31:0] $end
$var wire 32 e x18 [31:0] $end
$var wire 32 f x19 [31:0] $end
$var wire 32 g x20 [31:0] $end
$var wire 32 h x21 [31:0] $end
$var wire 32 i x22 [31:0] $end
$var wire 32 j x23 [31:0] $end
$var wire 32 k x24 [31:0] $end
$var wire 32 l x25 [31:0] $end
$var wire 32 m x26 [31:0] $end
$var wire 32 n x27 [31:0] $end
$var wire 32 o x28 [31:0] $end
$var wire 32 p x29 [31:0] $end
$var wire 32 q x30 [31:0] $end
$var wire 32 r x31 [31:0] $end
$var wire 5 s raddr1 [4:0] $end
$var wire 5 t raddr2 [4:0] $end
$var wire 5 u waddr [4:0] $end
$var reg 32 v wdata [31:0] $end
$var wire 32 w Instruction [31:0] $end
$var wire 32 L PC [31:0] $end
$var wire 32 x ALU_out [31:0] $end
$var wire 32 y Immediate_Value [31:0] $end
$var wire 32 z rdata [31:0] $end
$var reg 32 { A [31:0] $end
$var reg 32 | B [31:0] $end
$var wire 4 } alu_op [3:0] $end
$var wire 3 ~ br_type [2:0] $end
$var wire 2 !! wb_sel [1:0] $end
$var wire 1 "! sel_A $end
$var wire 1 #! sel_B $end
$var wire 1 I reg_wr $end
$var wire 1 $! br_taken $end
$var wire 1 %! unsign $end
$var wire 1 &! wr_en $end
$var wire 1 '! rd_en $end
$scope module rf $end
$var reg 32 ! rdata1 [31:0] $end
$var reg 32 " rdata2 [31:0] $end
$var reg 32 # x0 [31:0] $end
$var reg 32 $ x1 [31:0] $end
$var reg 32 % x2 [31:0] $end
$var reg 32 & x3 [31:0] $end
$var reg 32 ' x4 [31:0] $end
$var reg 32 ( x5 [31:0] $end
$var reg 32 ) x6 [31:0] $end
$var reg 32 * x7 [31:0] $end
$var reg 32 + x8 [31:0] $end
$var reg 32 , x9 [31:0] $end
$var reg 32 - x10 [31:0] $end
$var reg 32 . x11 [31:0] $end
$var reg 32 / x12 [31:0] $end
$var reg 32 0 x13 [31:0] $end
$var reg 32 1 x14 [31:0] $end
$var reg 32 2 x15 [31:0] $end
$var reg 32 3 x16 [31:0] $end
$var reg 32 4 x17 [31:0] $end
$var reg 32 5 x18 [31:0] $end
$var reg 32 6 x19 [31:0] $end
$var reg 32 7 x20 [31:0] $end
$var reg 32 8 x21 [31:0] $end
$var reg 32 9 x22 [31:0] $end
$var reg 32 : x23 [31:0] $end
$var reg 32 ; x24 [31:0] $end
$var reg 32 < x25 [31:0] $end
$var reg 32 = x26 [31:0] $end
$var reg 32 > x27 [31:0] $end
$var reg 32 ? x28 [31:0] $end
$var reg 32 @ x29 [31:0] $end
$var reg 32 A x30 [31:0] $end
$var reg 32 B x31 [31:0] $end
$var wire 5 C raddr1 [4:0] $end
$var wire 5 D raddr2 [4:0] $end
$var wire 5 E waddr [4:0] $end
$var wire 32 F wdata [31:0] $end
$var wire 1 G clk $end
$var wire 1 H rst $end
$var wire 1 I reg_wr $end
$var integer 32 J i $end
$upscope $end
$scope module im $end
$var reg 32 K Instruction [31:0] $end
$var wire 32 L Address [31:0] $end
$upscope $end
$scope module pc $end
$var wire 32 x ALU_out [31:0] $end
$var wire 1 $! br_taken $end
$var wire 1 G clk $end
$var wire 1 H rst $end
$var wire 1 O hard_write $end
$var reg 32 (! PC [31:0] $end
$upscope $end
$scope module ig $end
$var reg 32 )! Immediate_Value [31:0] $end
$var wire 32 w Instruction [31:0] $end
$var wire 1 %! unsign $end
$var wire 7 *! opcode [6:0] $end
$upscope $end
$scope module al $end
$var reg 32 +! ALU_out [31:0] $end
$var wire 32 ,! A [31:0] $end
$var wire 32 -! B [31:0] $end
$var wire 4 } alu_op [3:0] $end
$upscope $end
$scope module bcond $end
$var reg 1 .! br_taken $end
$var wire 32 Q A [31:0] $end
$var wire 32 R B [31:0] $end
$var wire 3 ~ br_type [2:0] $end
$upscope $end
$scope module dmem $end
$var reg 32 /! result [31:0] $end
$var reg 32 0! rdata [31:0] $end
$var wire 32 R wdata [31:0] $end
$var wire 32 x addr [31:0] $end
$var wire 32 M num1 [31:0] $end
$var wire 32 N num2 [31:0] $end
$var wire 1 &! wr_en $end
$var wire 1 '! rd_en $end
$var wire 1 G clk $end
$var wire 1 H rst $end
$var wire 1 O hard_write $end
$var integer 32 1! i $end
$upscope $end
$scope module cont $end
$var wire 32 w Instruction [31:0] $end
$var reg 4 2! alu_op [3:0] $end
$var reg 1 3! reg_wr $end
$var reg 1 4! sel_A $end
$var reg 1 5! sel_B $end
$var reg 1 6! wr_en $end
$var reg 1 7! rd_en $end
$var reg 1 8! unsign $end
$var reg 3 9! br_type [2:0] $end
$var reg 2 :! wb_sel [1:0] $end
$var wire 7 ;! opcode [6:0] $end
$var wire 7 <! func7 [6:0] $end
$var wire 3 =! func3 [2:0] $end
$upscope $end
$upscope $end
$upscope $end
$enddefinitions $end
#0
$dumpvars
b0 !
b0 !!
b0 "
0"!
b0 #
0#!
b0 $
0$!
b0 %
0%!
b0 &
0&!
b0 '
0'!
b0 (
b0 (!
b0 )
b0 )!
b0 *
b0 *!
b0 +
b0 +!
b0 ,
b0 ,!
b0 -
b0 -!
b0 .
0.!
b0 /
bx /!
b0 0
bx 0!
b0 1
b100000000 1!
b0 2
b0 2!
b0 3
03!
b0 4
04!
b0 5
05!
b0 6
06!
b0 7
07!
b0 8
08!
b0 9
b111 9!
b0 :
b0 :!
b0 ;
b0 ;!
b0 <
b0 <!
b0 =
b0 =!
b0 >
b0 ?
b0 @
b0 A
b0 B
b0 C
b0 D
b0 E
b100 F
1G
1H
0I
b100000 J
b0 K
b0 L
b10 M
b100 N
xO
bx P
b0 Q
b0 R
b0 S
b0 T
b0 U
b0 V
b0 W
b0 X
b0 Y
b0 Z
b0 [
b0 \
b0 ]
b0 ^
b0 _
b0 `
b0 a
b0 b
b0 c
b0 d
b0 e
b0 f
b0 g
b0 h
b0 i
b0 j
b0 k
b0 l
b0 m
b0 n
b0 o
b0 p
b0 q
b0 r
bz s
bz t
bz u
b100 v
b0 w
b0 x
b0 y
bx z
b0 {
b0 |
b0 }
b111 ~
$end
#5000
0G
#10000
b0 (!
b0 /!
b100000000 1!
1G
b100000 J
b0 P
#15000
0G
#20000
b0 (!
b0 /!
1G
0H
1O
#25000
0G
#30000
b0 (!
b0 /!
1G
#35000
0G
#40000
b10 !!
1#!
1'!
b100 (!
b0 )!
b11 *!
b0 /!
b10 0!
b0 2!
13!
04!
15!
06!
17!
08!
b111 9!
b10 :!
b11 ;!
b10 =!
b0 C
b0 D
b1000 E
b10 F
1G
1I
b10010000000011 K
b100 L
0O
b10 v
b10010000000011 w
b10 z
b0 {
b0 |
#45000
0G
#50000
b0 !
b0 "
b0 #
b0 $
b0 %
b0 &
b0 '
b0 (
b1000 (!
b0 )
b100 )!
b0 *
b10 +
b100 +!
b0 ,
b0 -
b100 -!
b0 .
b0 /
b0 /!
b0 0
b100 0!
b0 1
b0 2
b0 3
b0 4
b0 5
b0 6
b0 7
b0 8
b0 9
b0 :
b0 ;
b0 <
b0 =
b0 >
b0 ?
b0 @
b0 A
b0 B
b0 C
b100 D
b1001 E
b100 F
1G
b10000000010010010000011 K
b1000 L
b10 [
b100 v
b10000000010010010000011 w
b100 x
b100 y
b100 z
b0 {
b100 |
#55000
0G
#60000
b10 !
b0 !!
b100 "
1"!
b0 #
1#!
b0 $
0$!
b0 %
b0 &
b0 '
0'!
b0 (
b1100 (!
b0 )
b11000 )!
b0 *
b1100011 *!
b10 +
b100100 +!
b100 ,
b1100 ,!
b0 -
b11000 -!
b0 .
0.!
b0 /
b0 /!
b0 0
b0 1
b0 2
b0 2!
b0 3
03!
b0 4
14!
b0 5
15!
b0 6
06!
b0 7
07!
b0 8
08!
b0 9
b0 9!
b0 :
b0 :!
b0 ;
b1100011 ;!
b0 <
b0 =
b0 =!
b0 >
b0 ?
b0 @
b0 A
b0 B
b1000 C
b1001 D
b11000 E
b10000 F
1G
0I
b100101000000110001100011 K
b1100 L
b10 Q
b100 R
b100 \
b10000 v
b100101000000110001100011 w
b100100 x
b11000 y
b1100 {
b11000 |
b0 ~
#65000
0G
#70000
1"!
1#!
1$!
b10000 (!
b1100 )!
b11100 +!
b10000 ,!
b1100 -!
1.!
b0 /!
b0 2!
03!
14!
15!
06!
07!
08!
b10 9!
b0 :!
b100 =!
b1000 C
b1001 D
b1100 E
b10100 F
1G
b100101000100011001100011 K
b10000 L
b10100 v
b100101000100011001100011 w
b11100 x
b1100 y
b10000 {
b1100 |
b10 ~
#75000
0G
#80000
b100 !
b1 !!
b10 "
0"!
b0 #
0#!
b0 $
0$!
b0 %
b0 &
b0 '
1'!
b0 (
b11100 (!
b0 )
b0 )!
b0 *
b110011 *!
b10 +
b10 +!
b100 ,
b100 ,!
b0 -
b10 -!
b0 .
0.!
b0 /
b0 /!
b0 0
b10000000000000000000 0!
b0 1
b0 2
b111 2!
b0 3
13!
b0 4
04!
b0 5
05!
b0 6
06!
b0 7
17!
b0 8
08!
b0 9
b111 9!
b0 :
b1 :!
b0 ;
b110011 ;!
b0 <
b100000 <!
b0 =
b0 =!
b0 >
b0 ?
b0 @
b0 A
b0 B
b1001 C
b1000 D
b1001 E
b10 F
1G
1I
b1000000100001001000010010110011 K
b11100 L
b100 Q
b10 R
b10 v
b1000000100001001000010010110011 w
b10 x
b0 y
b10000000000000000000 z
b100 {
b10 |
b111 }
b111 ~
#85000
0G
#90000
b0 !
b0 !!
b0 "
1"!
b0 #
1#!
b0 $
1$!
b0 %
b0 &
b0 '
0'!
b0 (
b100000 (!
b0 )
b11111111111111111111111111101100 )!
b0 *
b1101111 *!
b10 +
b1100 +!
b10 ,
b100000 ,!
b0 -
b11111111111111111111111111101100 -!
b0 .
1.!
b0 /
b0 /!
b0 0
b0 1
b0 2
b0 2!
b0 3
13!
b0 4
14!
b0 5
15!
b0 6
06!
b0 7
07!
b0 8
08!
b0 9
b110 9!
b0 :
b0 :!
b0 ;
b1101111 ;!
b0 <
b1111111 <!
b0 =
b111 =!
b0 >
b0 ?
b0 @
b0 A
b0 B
b11111 C
b1101 D
b0 E
b100100 F
1G
1I
b11111110110111111111000001101111 K
b100000 L
b0 Q
b0 R
b10 \
b100100 v
b11111110110111111111000001101111 w
b1100 x
b11111111111111111111111111101100 y
b100000 {
b11111111111111111111111111101100 |
b0 }
b110 ~
#95000
0G
#100000
b10 !
b10 "
1"!
b0 #
1#!
b0 $
b0 %
b0 &
b0 '
b0 (
b1100 (!
b0 )
b11000 )!
b0 *
b1100011 *!
b10 +
b100100 +!
b10 ,
b1100 ,!
b0 -
b11000 -!
b0 .
1.!
b0 /
b0 /!
b0 0
b0 1
b0 2
b0 2!
b0 3
03!
b0 4
14!
b0 5
15!
b0 6
06!
b0 7
07!
b0 8
08!
b0 9
b0 9!
b0 :
b0 :!
b0 ;
b1100011 ;!
b0 <
b0 <!
b0 =
b0 =!
b0 >
b0 ?
b0 @
b0 A
b0 B
b1000 C
b1001 D
b11000 E
b10000 F
1G
0I
b100101000000110001100011 K
b1100 L
b10 Q
b10 R
b10000 v
b100101000000110001100011 w
b100100 x
b11000 y
b1100 {
b11000 |
b0 ~
#105000
0G
#110000
b0 !
b10 !!
b10 "
0"!
b0 #
1#!
b0 $
0$!
b0 %
b0 &
1&!
b0 '
b0 (
b100100 (!
b0 )
b1000 )!
b0 *
b100011 *!
b10 +
b1000 +!
b10 ,
b0 ,!
b0 -
b1000 -!
b0 .
0.!
b0 /
b0 /!
b0 0
b0 1
b0 2
b0 2!
b0 3
03!
b0 4
04!
b0 5
15!
b0 6
16!
b0 7
07!
b0 8
08!
b0 9
b111 9!
b0 :
b10 :!
b0 ;
b100011 ;!
b0 <
b0 =
b10 =!
b0 >
b0 ?
b0 @
b0 A
b0 B
b0 C
b1000 D
b1000 E
b10000000000000000000 F
1G
b100000000010010000100011 K
b100100 L
b0 Q
b10000000000000000000 v
b100000000010010000100011 w
b1000 x
b1000 y
b0 {
b1000 |
b111 ~
#115000
0G
#120000
b10 !!
1#!
0&!
1'!
b101000 (!
b1000 )!
b11 *!
b0 /!
b10 0!
b0 2!
13!
04!
15!
06!
17!
08!
b111 9!
b10 :!
b11 ;!
b0 C
b1000 D
b1010 E
b10 F
1G
1I
b100000000010010100000011 K
b101000 L
b10 v
b100000000010010100000011 w
b10 z
b0 {
b1000 |
#125000
0G
#130000
b0 !
b0 !!
b0 "
1"!
b0 #
1#!
b0 $
1$!
b0 %
b0 &
b0 '
0'!
b0 (
b101100 (!
b0 )
b0 )!
b0 *
b1101111 *!
b10 +
b101100 +!
b10 ,
b101100 ,!
b10 -
b0 -!
b0 .
1.!
b0 /
b10 /!
b0 0
b0 1
b0 2
b0 2!
b0 3
13!
b0 4
14!
b0 5
15!
b0 6
06!
b0 7
07!
b0 8
08!
b0 9
b110 9!
b0 :
b0 :!
b0 ;
b1101111 ;!
b0 <
b0 =
b0 =!
b0 >
b0 ?
b0 @
b0 A
b0 B
b0 C
b0 D
b0 E
b110000 F
1G
1I
b1101111 K
b101100 L
b10 P
b0 R
b10 ]
b110000 v
b1101111 w
b101100 x
b0 y
b101100 {
b0 |
b110 ~
#135000
0G
#140000
b101100 (!
b10 /!
1G
#145000
0G
#150000
0"!
0#!
0$!
b0 (!
b0 )!
b0 *!
b0 +!
b0 ,!
0.!
b10 /!
b0 2!
03!
04!
05!
06!
07!
08!
b111 9!
b0 :!
b0 ;!
b0 C
b0 D
b0 E
b100 F
1G
0I
b0 K
b0 L
b11110 M
b1111 N
1O
b100 v
b0 w
b0 x
b0 {
b0 |
b111 ~
#155000
0G
#160000
b0 (!
b10 /!
1G
#165000
0G
#170000
b10 !!
1#!
1'!
b100 (!
b0 )!
b11 *!
b10 /!
b10 0!
b0 2!
13!
04!
15!
06!
17!
08!
b111 9!
b10 :!
b11 ;!
b10 =!
b0 C
b0 D
b1000 E
b10 F
1G
1I
b10010000000011 K
b100 L
0O
b10 v
b10010000000011 w
b0 {
b0 |
#175000
0G
#180000
b0 !
b0 "
b0 #
b0 $
b0 %
b0 &
b0 '
b0 (
b1000 (!
b0 )
b100 )!
b0 *
b10 +
b100 +!
b10 ,
b10 -
b100 -!
b0 .
b0 /
b10 /!
b0 0
b100 0!
b0 1
b0 2
b0 3
b0 4
b0 5
b0 6
b0 7
b0 8
b0 9
b0 :
b0 ;
b0 <
b0 =
b0 >
b0 ?
b0 @
b0 A
b0 B
b0 C
b100 D
b1001 E
b100 F
1G
b10000000010010010000011 K
b1000 L
b100 v
b10000000010010010000011 w
b100 x
b100 y
b100 z
b0 {
b100 |
#185000
0G
#190000
b10 !
b0 !!
b100 "
1"!
b0 #
1#!
b0 $
0$!
b0 %
b0 &
b0 '
0'!
b0 (
b1100 (!
b0 )
b11000 )!
b0 *
b1100011 *!
b10 +
b100100 +!
b100 ,
b1100 ,!
b10 -
b11000 -!
b0 .
0.!
b0 /
b10 /!
b0 0
b0 1
b0 2
b0 2!
b0 3
03!
b0 4
14!
b0 5
15!
b0 6
06!
b0 7
07!
b0 8
08!
b0 9
b0 9!
b0 :
b0 :!
b0 ;
b1100011 ;!
b0 <
b0 =
b0 =!
b0 >
b0 ?
b0 @
b0 A
b0 B
b1000 C
b1001 D
b11000 E
b10000 F
1G
0I
b100101000000110001100011 K
b1100 L
b10 Q
b100 R
b100 \
b10000 v
b100101000000110001100011 w
b100100 x
b11000 y
b1100 {
b11000 |
b0 ~
#195000
0G
#200000
1"!
1#!
1$!
b10000 (!
b1100 )!
b11100 +!
b10000 ,!
b1100 -!
1.!
b10 /!
b0 2!
03!
14!
15!
06!
07!
08!
b10 9!
b0 :!
b100 =!
b1000 C
b1001 D
b1100 E
b10100 F
1G
b100101000100011001100011 K
b10000 L
b10100 v
b100101000100011001100011 w
b11100 x
b1100 y
b10000 {
b1100 |
b10 ~
#205000
0G
