Lab3/Program_Counter.sv
module Program_Counter (
    input [31:0] ALU_out,
    input br_taken, clk, rst,
    output reg [31:0] PC
);
    always @(posedge clk ) begin
        if(rst)
            PC <= 0;
        else
            PC <= br_taken ? ALU_out : PC + 4;
    end
    
endmodule

Lab3/Instruction_Memory.sv
module Instruction_Memory (
    output reg [31:0] Instruction,
    input [31:0] Address
);
    reg [31:0] instruction_memory [50:0];
    initial begin
     $readmemh("instruction_mem.mem",instruction_memory);
    end

    always @(*) begin
        Instruction <= instruction_memory[Address/4];
    end

    initial begin
        $dumpfile("dump.vcd");
        $dumpvars;
    end
    
endmodule

Lab3/Register_File.sv
module Register_File (
    output reg [31:0] rdata1, rdata2,
    output reg [31:0] x0,x1,x2,x3,x4,x5,x6,x7,x8,x9,x10,x11,x12,x13,x14,x15,x16,x17,x18,x19,x20,x21,x22,x23,x24,x25,x26,x27,x28,x29,x30,x31,
    input [4:0] raddr1, raddr2, waddr,
    input [31:0] wdata,
    input clk, rst, reg_wr
);
    integer i;
    reg [31:0] register_file [31:0];
    always @(posedge clk ) begin
        if(rst) begin
            for (i = 0; i <= 31; i=i+1) begin
                register_file[i] <= 0;
            end
        end else if(reg_wr) begin
            if(waddr != 0)
                register_file[waddr] <= wdata;
        end 
    end

    always @(*) begin
        rdata1 <= register_file[raddr1];
        rdata2 <= register_file[raddr2];
        x0 <= register_file[0];
        x1 <= register_file[1];
        x2 <= register_file[2];
        x3 <= register_file[3];
        x4 <= register_file[4];
        x5 <= register_file[5];
        x6 <= register_file[6];
        x7 <= register_file[7];
        x8 <= register_file[8];
        x9 <= register_file[9];
        x10 <= register_file[10];
        x11 <= register_file[11];
        x12 <= register_file[12];
        x13 <= register_file[13];
        x14 <= register_file[14];
        x15 <= register_file[15];
        x16 <= register_file[16];
        x17 <= register_file[17];
        x18 <= register_file[18];
        x19 <= register_file[19];
        x20 <= register_file[20];
        x21 <= register_file[21];
        x22 <= register_file[22];
        x23 <= register_file[23];
        x24 <= register_file[24];
        x25 <= register_file[25];
        x26 <= register_file[26];
        x27 <= register_file[27];
        x28 <= register_file[28];
        x29 <= register_file[29];
        x30 <= register_file[30];
        x31 <= register_file[31];
    end

    initial begin
        $dumpfile("dump.vcd");
        $dumpvars;
    end
    
endmodule

Lab3/top.sv
`include "Register_File.sv"
`include "Instruction_Memory.sv"
`include "Program_Counter.sv"
`timescale 1ns/1ns

module top(
    input clk, rst
);
    
    wire[31:0] rdata1, rdata2;
    wire [31:0]x0,x1,x2,x3,x4,x5,x6,x7,x8,x9,x10,x11,x12,x13,x14,x15,x16,x17,x18,x19,x20,x21,x22,x23,x24,x25,x26,x27,x28,x29,x30,x31;
    input [4:0] raddr1, raddr2, waddr;
    input [31:0] wdata;

    Register_File r1(.rdata1(rdata1), .rdata2(rdata2), 
    .x0(x0), .x1(x1), .x2(x2), .x3(x3), .x4(x4), .x5(x5), .x6(x6), .x7(x7), .x8(x8), .x9(x9), .x10(x10), .x11(x11), .x12(x12), .x13(x13), .x14(x14),
    .x15(x15), .x16(x16), .x17(x17), .x18(x18), .x19(x19), .x20(x20), .x21(x21), .x22(x22), .x23(x23), .x24(x24), .x25(x25), .x26(x26), .x27(x27),
    .x28(x28), .x29(x29), .x30(x30), .x31(x31),
    .raddr1(raddr1), .raddr2(raddr2), .waddr(waddr), .wdata(wdata), .clk(clk), .rst(rst), .reg_wr(reg_wr));

    wire [31:0] Instruction, PC, ALU_out;

    Instruction_Memory i1(.Instruction(Instruction), .Address(PC));

    Program_Counter p1(.ALU_out(ALU_out), .br_taken(br_taken), .clk(clk), .rst(rst), .PC(PC));

    initial begin
        $dumpfile("dump.vcd");
        $dumpvars;
    end
    
endmodule

Lab3/dump.vcd
$date
	Sun Oct 17 17:00:31 2021
$end
$version
	Icarus Verilog
$end
$timescale
	1ps
$end
$scope module top $end
$var wire 32 ! ALU_out [31:0] $end
$var wire 1 " br_taken $end
$var wire 1 # clk $end
$var wire 5 $ raddr1 [4:0] $end
$var wire 5 % raddr2 [4:0] $end
$var wire 1 & reg_wr $end
$var wire 1 ' rst $end
$var wire 5 ( waddr [4:0] $end
$var wire 32 ) wdata [31:0] $end
$var wire 32 * x9 [31:0] $end
$var wire 32 + x8 [31:0] $end
$var wire 32 , x7 [31:0] $end
$var wire 32 - x6 [31:0] $end
$var wire 32 . x5 [31:0] $end
$var wire 32 / x4 [31:0] $end
$var wire 32 0 x31 [31:0] $end
$var wire 32 1 x30 [31:0] $end
$var wire 32 2 x3 [31:0] $end
$var wire 32 3 x29 [31:0] $end
$var wire 32 4 x28 [31:0] $end
$var wire 32 5 x27 [31:0] $end
$var wire 32 6 x26 [31:0] $end
$var wire 32 7 x25 [31:0] $end
$var wire 32 8 x24 [31:0] $end
$var wire 32 9 x23 [31:0] $end
$var wire 32 : x22 [31:0] $end
$var wire 32 ; x21 [31:0] $end
$var wire 32 < x20 [31:0] $end
$var wire 32 = x2 [31:0] $end
$var wire 32 > x19 [31:0] $end
$var wire 32 ? x18 [31:0] $end
$var wire 32 @ x17 [31:0] $end
$var wire 32 A x16 [31:0] $end
$var wire 32 B x15 [31:0] $end
$var wire 32 C x14 [31:0] $end
$var wire 32 D x13 [31:0] $end
$var wire 32 E x12 [31:0] $end
$var wire 32 F x11 [31:0] $end
$var wire 32 G x10 [31:0] $end
$var wire 32 H x1 [31:0] $end
$var wire 32 I x0 [31:0] $end
$var wire 32 J rdata2 [31:0] $end
$var wire 32 K rdata1 [31:0] $end
$var wire 32 L PC [31:0] $end
$var wire 32 M Instruction [31:0] $end
$scope module i1 $end
$var wire 32 N Address [31:0] $end
$var reg 32 O Instruction [31:0] $end
$upscope $end
$scope module p1 $end
$var wire 32 P ALU_out [31:0] $end
$var wire 1 " br_taken $end
$var wire 1 # clk $end
$var wire 1 ' rst $end
$var reg 32 Q PC [31:0] $end
$upscope $end
$scope module r1 $end
$var wire 1 # clk $end
$var wire 5 R raddr1 [4:0] $end
$var wire 5 S raddr2 [4:0] $end
$var wire 1 & reg_wr $end
$var wire 1 ' rst $end
$var wire 5 T waddr [4:0] $end
$var wire 32 U wdata [31:0] $end
$var reg 32 V rdata1 [31:0] $end
$var reg 32 W rdata2 [31:0] $end
$var reg 32 X x0 [31:0] $end
$var reg 32 Y x1 [31:0] $end
$var reg 32 Z x10 [31:0] $end
$var reg 32 [ x11 [31:0] $end
$var reg 32 \ x12 [31:0] $end
$var reg 32 ] x13 [31:0] $end
$var reg 32 ^ x14 [31:0] $end
$var reg 32 _ x15 [31:0] $end
$var reg 32 ` x16 [31:0] $end
$var reg 32 a x17 [31:0] $end
$var reg 32 b x18 [31:0] $end
$var reg 32 c x19 [31:0] $end
$var reg 32 d x2 [31:0] $end
$var reg 32 e x20 [31:0] $end
$var reg 32 f x21 [31:0] $end
$var reg 32 g x22 [31:0] $end
$var reg 32 h x23 [31:0] $end
$var reg 32 i x24 [31:0] $end
$var reg 32 j x25 [31:0] $end
$var reg 32 k x26 [31:0] $end
$var reg 32 l x27 [31:0] $end
$var reg 32 m x28 [31:0] $end
$var reg 32 n x29 [31:0] $end
$var reg 32 o x3 [31:0] $end
$var reg 32 p x30 [31:0] $end
$var reg 32 q x31 [31:0] $end
$var reg 32 r x4 [31:0] $end
$var reg 32 s x5 [31:0] $end
$var reg 32 t x6 [31:0] $end
$var reg 32 u x7 [31:0] $end
$var reg 32 v x8 [31:0] $end
$var reg 32 w x9 [31:0] $end
$var integer 32 x i [31:0] $end
$upscope $end
$upscope $end
$scope module top $end
$scope module i1 $end
$upscope $end
$scope module p1 $end
$upscope $end
$scope module r1 $end
$upscope $end
$upscope $end
$scope module top $end
$scope module i1 $end
$upscope $end
$scope module p1 $end
$upscope $end
$scope module r1 $end
$upscope $end
$upscope $end
$enddefinitions $end
#0
$dumpvars
bx x
bx w
bx v
bx u
bx t
bx s
bx r
bx q
bx p
bx o
bx n
bx m
bx l
bx k
bx j
bx i
bx h
bx g
bx f
bx e
bx d
bx c
bx b
bx a
bx `
bx _
bx ^
bx ]
bx \
bx [
bx Z
bx Y
bx X
bx W
bx V
bz U
bz T
bz S
bz R
bx Q
b1010 P
bx O
bx N
bx M
bx L
bx K
bx J
bx I
bx H
bx G
bx F
bx E
bx D
bx C
bx B
bx A
bx @
bx ?
bx >
bx =
bx <
bx ;
bx :
bx 9
bx 8
bx 7
bx 6
bx 5
bx 4
bx 3
bx 2
bx 1
bx 0
bx /
bx .
bx -
bx ,
bx +
bx *
bz )
bz (
1'
z&
bz %
bz $
1#
0"
b1010 !
$end
#5000
0#
#10000
0'
b101101011000010100010011 M
b101101011000010100010011 O
b0 0
b0 q
b0 1
b0 p
b0 3
b0 n
b0 4
b0 m
b0 5
b0 l
b0 6
b0 k
b0 7
b0 j
b0 8
b0 i
b0 9
b0 h
b0 :
b0 g
b0 ;
b0 f
b0 <
b0 e
b0 >
b0 c
b0 ?
b0 b
b0 @
b0 a
b0 A
b0 `
b0 B
b0 _
b0 C
b0 ^
b0 D
b0 ]
b0 E
b0 \
b0 F
b0 [
b0 G
b0 Z
b0 *
b0 w
b0 +
b0 v
b0 ,
b0 u
b0 -
b0 t
b0 .
b0 s
b0 /
b0 r
b0 2
b0 o
b0 =
b0 d
b0 H
b0 Y
b0 L
b0 N
b0 Q
b100000 x
1#
#15000
0#
#20000
b1000000101101010000010100110011 M
b1000000101101010000010100110011 O
b100 L
b100 N
b100 Q
1#
#25000
0#
#30000
b101101010101010100110011 M
b101101010101010100110011 O
b1000 L
b1000 N
b1000 Q
1#
#35000
0#
#40000
1"
bx M
bx O
b1100 L
b1100 N
b1100 Q
1#
#45000
0#
#50000
0"
b101101010101010100110011 M
b101101010101010100110011 O
b1010 L
b1010 N
b1010 Q
1#
#55000
0#
#60000
bx M
bx O
b1110 L
b1110 N
b1110 Q
1#
#65000
0#
#70000
b10010 L
b10010 N
b10010 Q
1#
